{
  "basics": {
    "name": "Jane Doe",
    "label": "Computer Science Student",
    "picture": "https://example.com/jane-doe.jpg",
    "email": "jane.doe@university.edu",
    "phone": "(555) 123-4567",
    "website": "https://janedoe.dev",
    "summary": "Passionate Computer Science undergraduate at State University. Active in open-source, hackathons, and research on machine learning. Seeking internship opportunities to apply skills in full-stack development and data science.",
    "location": {
      "address": "123 University Ave",
      "postalCode": "12345",
      "city": "College Town",
      "countryCode": "US",
      "region": "CA"
    },
    "profiles": [
      {
        "network": "GitHub",
        "username": "janedoe",
        "url": "https://github.com/janedoe"
      },
      {
        "network": "LinkedIn",
        "username": "jane-doe",
        "url": "https://www.linkedin.com/in/jane-doe"
      }
    ]
  },
  "education": [
    {
      "institution": "State University",
      "area": "Computer Science",
      "studyType": "B.S.",
      "startDate": "2021-08-01",
      "endDate": "2025-05-01",
      "gpa": "3.85",
      "courses": [
        "Data Structures & Algorithms",
        "Operating Systems",
        "Machine Learning",
        "Databases"
      ]
    },
    {
      "institution": "Central High School",
      "area": "Science & Math",
      "studyType": "High School Diploma",
      "startDate": "2017-09-01",
      "endDate": "2021-06-01",
      "gpa": "4.00",
      "courses": [
        "AP Computer Science A",
        "AP Calculus AB"
      ]
    }
  ],
  "projects": [
    {
      "name": "Campus Connect",
      "description": "A React Native mobile app to help students find campus events and form study groups.",
      "highlights": [
        "Implemented real-time chat with Socket.io",
        "Integrated Google Calendar API for event scheduling",
        "Deployed to Expo and published on TestFlight"
      ],
      "keywords": [
        "React Native",
        "Node.js",
        "Firebase"
      ],
      "startDate": "2023-02-01",
      "endDate": "2023-05-01",
      "url": "https://github.com/janedoe/campus-connect"
    },
    {
      "name": "Data Structures Visualizer",
      "description": "Web application to visualize how common data structures operate.",
      "highlights": [
        "Animated insert, delete, and search operations in JavaScript",
        "Designed UI with D3.js",
        "Deployed on GitHub Pages"
      ],
      "keywords": [
        "D3.js",
        "HTML",
        "CSS",
        "JavaScript"
      ],
      "startDate": "2022-11-01",
      "endDate": "2023-01-15",
      "url": "https://janedoe.github.io/ds-visualizer"
    }
  ],
  "certificates": [
    {
      "name": "Machine Learning",
      "issuer": "Stanford University (Coursera)",
      "date": "2022-08-01",
      "url": "https://coursera.org/verify/ML-JaneDoe"
    },
    {
      "name": "Front-End Web Developer",
      "issuer": "freeCodeCamp",
      "date": "2023-03-01",
      "url": "https://www.freecodecamp.org/certification/janedoe/front-end"
    }
  ],
  "work": [
    {
      "company": "TechStart Labs",
      "position": "Software Engineering Intern",
      "website": "https://techstartlabs.com",
      "startDate": "2024-06-01",
      "endDate": "2024-08-31",
      "summary": "Worked on the backend team to build RESTful APIs for a B2B analytics dashboard.",
      "highlights": [
        "Designed and implemented endpoints in Express.js",
        "Wrote unit tests with Jest achieving 90% coverage",
        "Collaborated in Agile sprints and code reviews"
      ]
    }
  ],
  "volunteer": [
    {
      "organization": "Girls Who Code",
      "position": "Mentor",
      "website": "https://girlswhocode.com",
      "startDate": "2023-09-01",
      "endDate": "2024-05-01",
      "summary": "Guided high-school students through Python and web development projects."
    }
  ],
  "skills": [
    {
      "name": "Programming Languages",
      "level": "Intermediate",
      "keywords": [
        "JavaScript",
        "Python",
        "Java",
        "C++"
      ]
    },
    {
      "name": "Web & Mobile",
      "level": "Intermediate",
      "keywords": [
        "React",
        "Node.js",
        "React Native",
        "Django"
      ]
    },
    {
      "name": "Data Science",
      "level": "Beginner",
      "keywords": [
        "Pandas",
        "scikit-learn",
        "TensorFlow"
      ]
    }
  ],
  "languages": [
    {
      "language": "English",
      "fluency": "Native speaker"
    },
    {
      "language": "Spanish",
      "fluency": "Conversational"
    }
  ],
  "interests": [
    {
      "name": "Hackathons",
      "keywords": [
        "MLH Localhost",
        "Hack the North"
      ]
    },
    {
      "name": "Open Source",
      "keywords": [
        "Contributor at Mozilla",
        "React community"
      ]
    }
  ],
  "awards": [
    {
      "title": "Dean’s List",
      "date": "2023-06-01",
      "awarder": "State University",
      "summary": "Recognized for academic excellence (GPA ≥ 3.75)."
    }
  ]
}